{
  "English - United States": "en",                 
  "English - United Kingdom": "en",               
  "Mandarin Chinese - China": "zh",                 
  "Mandarin Chinese - Taiwan": "zh",                
  "Hindi - India": "hi",                            
  "Spanish - Spain": "es",                          
  "Spanish - Latin America": "es",                 
  "French - France": "fr",                          
  "French - Canada": "fr",                          
  "Arabic - Modern Standard": "ar",                 
  "Arabic - Egypt": "ar",                          
  "Arabic - Saudi Arabia": "ar",                  
  "Bengali - Bangladesh": "bn",                     
  "Portuguese - Brazil": "pt",                      
  "Portuguese - Portugal": "pt",                    
  "Russian - Russia": "ru",                         
  "Japanese - Japan": "ja",                         
  "Punjabi - India": "pa",                          
  "German - Germany": "de",                         
  "Korean - South Korea": "ko",                     
  "Vietnamese - Vietnam": "vi",                     
  "Telugu - India": "te",                           
  "Turkish - Turkey": "tr",                         
  "Italian - Italy": "it",                          
  "Tamil - India": "ta",                            
  "Persian - Iran": "fa",                           
  "Polish - Poland": "pl",                          
  "Ukrainian - Ukraine": "uk",                      
  "Dutch - Netherlands": "nl",                      
  "Indonesian - Indonesia": "id",                   
  "Thai - Thailand": "th",                          
  "Greek - Greece": "el",                           
  "Hungarian - Hungary": "hu",                      
  "Swedish - Sweden": "sv",                         
  "Czech - Czech Republic": "cs",                   
  "Romanian - Romania": "ro",                       
  "Hebrew - Israel": "he",                          
  "Malay - Malaysia": "ms",                         
  "Tagalog - Philippines": "tl",                    
  "Danish - Denmark": "da",                         
  "Finnish - Finland": "fi",                        
  "Norwegian - Norway": "no",                       
  "Swahili - Kenya": "sw",                          
  "Amharic - Ethiopia": "am",                       
  "Afrikaans - South Africa": "af",                 
  "Uzbek - Uzbekistan": "uz",                       
  "Kazakh - Kazakhstan": "kk",                      
  "Azerbaijani - Azerbaijan": "az",                 
  "Serbian - Serbia": "sr",                         
  "Croatian - Croatia": "hr",                       
  "Slovak - Slovakia": "sk",                        
  "Bulgarian - Bulgaria": "bg",                     
  "Slovenian - Slovenia": "sl",                     
  "Lithuanian - Lithuania": "lt",                   
  "Latvian - Latvia": "lv",                         
  "Estonian - Estonia": "et",                       
  "Georgian - Georgia": "ka",                       
  "Armenian - Armenia": "hy",                       
  "Albanian - Albania": "sq",                       
  "Macedonian - North Macedonia": "mk",             
  "Mongolian - Mongolia": "mn",                     
  "Bosnian - Bosnia and Herzegovina": "bs",         
  "Sinhala - Sri Lanka": "si",                      
  "Zulu - South Africa": "zu",                      
  "Xhosa - South Africa": "xh",                     
  "Irish - Ireland": "ga",                          
  "Welsh - Wales": "cy",                            
  "Basque - Spain": "eu",                           
  "Catalan - Spain": "ca",                          
  "Galician - Spain": "gl",                       
  "Icelandic - Iceland": "is",                     
  "Maltese - Malta": "mt"                   
}